{
  "configurations": [
    {
      "name": "x64-Release",
      "generator": "Visual Studio 17 2022",
      "configurationType": "Release",
      "buildRoot": "${projectDir}\\build\\${name}",
      "installRoot": "${projectDir}\\install\\${name}",
      "cmakeCommandArgs": "",
      "buildCommandArgs": "",
      "ctestCommandArgs": "",
      "inheritEnvironments": [ "msvc_x64_x64" ],
      "variables": [
        {
          "name": "CMAKE_TOOLCHAIN_FILE",
          "value": "C:/vcpkg/scripts/buildsystems/vcpkg.cmake",
          "type": "PATH"
        },
        {
          "name": "VCPKG_TARGET_TRIPLET",
          "value": "x64-windows-static",
          "type": "STRING"
        }
      ]
    }
  ]
} 